client/__init__.py
client/data_client.py
client/test.py
client/test_utils.py
client/client/__init__.py
client/client/add_contact.py
client/client/client_db.py
client/client/del_contact.py
client/client/main_window.py
client/client/main_window_conv.py
client/client/start_dialog.py
client/client/transport.py
client/logs/__init__.py
client/logs/client_log_config.py
client/logs/decor_log.py
client/logs/server_log_config.py
client/utils/__init__.py
client/utils/descriptors.py
client/utils/errors.py
client/utils/login_required.py
client/utils/metaclasses.py
client/utils/utils.py
client_chat_pyqt_still190494-0.1.dist-info/METADATA
client_chat_pyqt_still190494-0.1.dist-info/WHEEL
client_chat_pyqt_still190494-0.1.dist-info/top_level.txt
client_chat_pyqt_still190494-0.1.dist-info/RECORD
